taskbutler/__init__.py
taskbutler/cli.py
taskbutler/config.ini.sample
taskbutler/config.py
taskbutler/taskbutler.py
taskbutler/helpers/__init__.py
taskbutler/helpers/github.py
taskbutler-2.2.5.dist-info/LICENSE
taskbutler-2.2.5.dist-info/METADATA
taskbutler-2.2.5.dist-info/WHEEL
taskbutler-2.2.5.dist-info/entry_points.txt
taskbutler-2.2.5.dist-info/top_level.txt
taskbutler-2.2.5.dist-info/RECORD
