Metadata-Version: 2.1
Name: taskbutler
Version: 2.2.5
Summary: Taskbutler enriches your Todoist tasks by adding progress bars, Office365 Files and Dropbox Paper papers directly to your tasks.
Home-page: https://github.com/6uhrmittag/taskbutler
Author: Marvin Heimbrodt
Author-email: marvin@6uhrmittag.de
License: MIT license
Keywords: taskbutler
Platform: UNKNOWN
Classifier: Development Status :: 5 - Production/Stable
Classifier: Intended Audience :: Developers
Classifier: License :: OSI Approved :: MIT License
Classifier: Natural Language :: English
Classifier: Programming Language :: Python :: 3.4
Classifier: Programming Language :: Python :: 3.5
Classifier: Programming Language :: Python :: 3.6
Classifier: Programming Language :: Python :: 3.7
Requires-Dist: Click (>=6.0)
Requires-Dist: todoist-python
Requires-Dist: PyGithub
Requires-Dist: requests
Requires-Dist: dropbox
